{
  "m_GameObject": {
    "m_FileID": 0,
    "m_PathID": 114
  },
  "m_Enabled": 1,
  "m_Script": {
    "m_FileID": 1,
    "m_PathID": 550
  },
  "m_Name": "",
  "defeatFlagID": 139,
  "counterFlagID": 140,
  "killExhaustCount": 1,
  "battleId": 46,
  "npcRespawn": {
    "m_FileID": 0,
    "m_PathID": 0
  },
  "hardModeBattleID": -1,
  "hardModeNpcRespawn": {
    "m_FileID": 0,
    "m_PathID": 0
  },
  "instantSpareRespawn": 0,
  "deadPrefab": {
    "m_FileID": 2,
    "m_PathID": 18033
  },
  "startLook": {
    "x": -1.0,
    "y": 0.0
  }
}